{\n  "id": 115,\n  "groups": {\n    "CHRISTMAS-RELATED": {\n      "level": 0,\n      "members": [\n        "MISTLETOE",\n        "REINDEER",\n        "SNOWMAN",\n        "STOCKING"\n      ]\n    },\n    "MAKE PUBLIC": {\n      "level": 1,\n      "members": [\n        "DISPLAY",\n        "EXHIBIT",\n        "PRESENT",\n        "SHOW"\n      ]\n    },\n    "TORUS-SHAPED FOOD": {\n      "level": 2,\n      "members": [\n        "BAGEL",\n        "CHEERIO",\n        "DONUT",\n        "LIFESAVER"\n      ]\n    },\n    "THINGS WITH STRIPES": {\n      "level": 3,\n      "members": [\n        "CANDY CANE",\n        "CROSSWALK",\n        "REFEREE",\n        "TIGER"\n      ]\n    }\n  },\n  "startingGroups": [\n    [\n      "SHOW",\n      "DONUT",\n      "STOCKING",\n      "TIGER"\n    ],\n    [\n      "LIFESAVER",\n      "PRESENT",\n      "CANDY CANE",\n      "SNOWMAN"\n    ],\n    [\n      "REINDEER",\n      "CHEERIO",\n      "EXHIBIT",\n      "REFEREE"\n    ],\n    [\n      "BAGEL",\n      "DISPLAY",\n      "CROSSWALK",\n      "MISTLETOE"\n    ]\n  ]\n}