{\n  "id": 268,\n  "groups": {\n    "PROPEL INTO THE AIR": {\n      "level": 0,\n      "members": [\n        "HOP",\n        "JUMP",\n        "LEAP",\n        "SPRING"\n      ]\n    },\n    "PLACE TO STORE VALUABLES": {\n      "level": 1,\n      "members": [\n        "CHEST",\n        "COFFER",\n        "SAFE",\n        "VAULT"\n      ]\n    },\n    "PERIOD": {\n      "level": 2,\n      "members": [\n        "AGE",\n        "DAY",\n        "ERA",\n        "TIME"\n      ]\n    },\n    "ANIMALS BACKWARD": {\n      "level": 3,\n      "members": [\n        "DRIB",\n        "FLOW",\n        "REED",\n        "TANG"\n      ]\n    }\n  },\n  "startingGroups": [\n    [\n      "LEAP",\n      "DAY",\n      "SAFE",\n      "TANG"\n    ],\n    [\n      "FLOW",\n      "VAULT",\n      "AGE",\n      "JUMP"\n    ],\n    [\n      "SPRING",\n      "TIME",\n      "DRIB",\n      "CHEST"\n    ],\n    [\n      "ERA",\n      "COFFER",\n      "HOP",\n      "REED"\n    ]\n  ]\n}